dynamic_genetic_algo/__init__.py
dynamic_genetic_algo/cluster_analysis.py
dynamic_genetic_algo/genetic_algorithm.py
dynamic_genetic_algo-3.0.0.dist-info/METADATA
dynamic_genetic_algo-3.0.0.dist-info/WHEEL
dynamic_genetic_algo-3.0.0.dist-info/top_level.txt
dynamic_genetic_algo-3.0.0.dist-info/RECORD
